ariadne_codegen/__about__.py
ariadne_codegen/__init__.py
ariadne_codegen/__main__.py
ariadne_codegen/codegen.py
ariadne_codegen/config.py
ariadne_codegen/exceptions.py
ariadne_codegen/main.py
ariadne_codegen/py.typed
ariadne_codegen/schema.py
ariadne_codegen/settings.py
ariadne_codegen/utils.py
ariadne_codegen/client_generators/__init__.py
ariadne_codegen/client_generators/arguments.py
ariadne_codegen/client_generators/client.py
ariadne_codegen/client_generators/comments.py
ariadne_codegen/client_generators/constants.py
ariadne_codegen/client_generators/custom_arguments.py
ariadne_codegen/client_generators/custom_fields.py
ariadne_codegen/client_generators/custom_fields_typing.py
ariadne_codegen/client_generators/custom_generator_utils.py
ariadne_codegen/client_generators/custom_operation.py
ariadne_codegen/client_generators/enums.py
ariadne_codegen/client_generators/fragments.py
ariadne_codegen/client_generators/init_file.py
ariadne_codegen/client_generators/input_fields.py
ariadne_codegen/client_generators/input_types.py
ariadne_codegen/client_generators/package.py
ariadne_codegen/client_generators/result_fields.py
ariadne_codegen/client_generators/result_types.py
ariadne_codegen/client_generators/scalars.py
ariadne_codegen/client_generators/types.py
ariadne_codegen/client_generators/dependencies/__init__.py
ariadne_codegen/client_generators/dependencies/async_base_client.py
ariadne_codegen/client_generators/dependencies/async_base_client_open_telemetry.py
ariadne_codegen/client_generators/dependencies/base_client.py
ariadne_codegen/client_generators/dependencies/base_client_open_telemetry.py
ariadne_codegen/client_generators/dependencies/base_model.py
ariadne_codegen/client_generators/dependencies/base_operation.py
ariadne_codegen/client_generators/dependencies/exceptions.py
ariadne_codegen/contrib/__init__.py
ariadne_codegen/contrib/client_forward_refs.py
ariadne_codegen/contrib/extract_operations.py
ariadne_codegen/contrib/no_reimports.py
ariadne_codegen-0.17.1.dist-info/METADATA
ariadne_codegen-0.17.1.dist-info/WHEEL
ariadne_codegen-0.17.1.dist-info/entry_points.txt
ariadne_codegen-0.17.1.dist-info/licenses/LICENSE
ariadne_codegen-0.17.1.dist-info/RECORD
