Metadata-Version: 2.4
Name: ariadne-codegen
Version: 0.17.1
Summary: Generate fully typed GraphQL client from schema, queries and mutations!
Project-URL: Homepage, https://ariadnegraphql.org/
Project-URL: Repository, https://github.com/mirumee/ariadne-codegen
Project-URL: Bug Tracker, https://github.com/mirumee/ariadne-codegen/issues
Project-URL: Community, https://github.com/mirumee/ariadne/discussions
Project-URL: Twitter, https://twitter.com/AriadneGraphQL
Author-email: Mirumee Software <ariadne@mirumee.com>
License-Expression: BSD-3-Clause
License-File: LICENSE
Classifier: Development Status :: 4 - Beta
Classifier: Intended Audience :: Developers
Classifier: License :: OSI Approved :: BSD License
Classifier: Operating System :: OS Independent
Classifier: Programming Language :: Python
Classifier: Programming Language :: Python :: 3.10
Classifier: Programming Language :: Python :: 3.11
Classifier: Programming Language :: Python :: 3.12
Classifier: Programming Language :: Python :: 3.13
Classifier: Programming Language :: Python :: 3.14
Classifier: Topic :: Software Development :: Libraries :: Python Modules
Requires-Python: >=3.10
Requires-Dist: autoflake
Requires-Dist: black
Requires-Dist: click~=8.3
Requires-Dist: graphql-core<3.3,>=3.2.0
Requires-Dist: httpx~=0.28
Requires-Dist: isort
Requires-Dist: pydantic<3.0.0,>=2.0.0
Requires-Dist: toml~=0.10
Provides-Extra: dev
Requires-Dist: ipdb; extra == 'dev'
Provides-Extra: opentelemetry
Requires-Dist: opentelemetry-api; extra == 'opentelemetry'
Provides-Extra: subscriptions
Requires-Dist: websockets>=15; extra == 'subscriptions'
Provides-Extra: test
Requires-Dist: ariadne; extra == 'test'
Requires-Dist: freezegun; extra == 'test'
Requires-Dist: opentelemetry-api; extra == 'test'
Requires-Dist: pytest; extra == 'test'
Requires-Dist: pytest-asyncio; extra == 'test'
Requires-Dist: pytest-httpx; extra == 'test'
Requires-Dist: pytest-mock; extra == 'test'
Requires-Dist: requests-toolbelt; extra == 'test'
Requires-Dist: types-toml; extra == 'test'
Requires-Dist: websockets>=14.2; extra == 'test'
Provides-Extra: types
Requires-Dist: mypy>=1.19.0; extra == 'types'
